setup.py
probability_distributions_gb/Binomialdistribution.py
probability_distributions_gb/Gaussiandistribution.py
probability_distributions_gb/Generaldistribution.py
probability_distributions_gb/__init__.py
probability_distributions_gb.egg-info/PKG-INFO
probability_distributions_gb.egg-info/SOURCES.txt
probability_distributions_gb.egg-info/dependency_links.txt
probability_distributions_gb.egg-info/not-zip-safe
probability_distributions_gb.egg-info/top_level.txt