Metadata-Version: 1.0
Name: probability-distributions-gb
Version: 1.1
Summary: Gaussian and Binomial distributions
Home-page: UNKNOWN
Author: Ansh Srivastava
Author-email: UNKNOWN
License: UNKNOWN
Platform: UNKNOWN
